[
  {
    "brand": "Distorting Decibels",
    "tagline": "Let Out the Melodies!",
    "logo": "",
    "logoAlt": "Distorting Decibels Logo",
    "snowGlobe": "YES",
    "snowColor": "#F0F6FCAA",
    "audio": "NO",
    "audioURL": ""
  },
  {
    "blocks": [
      {
        "name": "Like us on Facebook",
        "link": "https://www.facebook.com/Distorting.Decibels/",
		"newTab": "YES",
		"png": "img/social-facebook.png",
		"id": "facebook"
      },
      {
        "name": "Join our Facebook Group",
        "link": "https://www.facebook.com/groups/discobels/",
		"newTab": "YES",
		"png": "img/social-fbgroup.png",
		"id": "facebook-group"
      },
      {
        "name": "Follow us on Instagram",
        "link": "https://www.instagram.com/distorting.decibels/",
		"newTab": "YES",
		"png": "img/social-instagram.png",
		"id": "instagram"
      },
      {
        "name": "Follow us on Twitter",
        "link": "https://twitter.com/DistortingD",
		"newTab": "YES",
		"png": "img/social-twitter.png",
		"id": "twitter"
      },
	  {
        "name": "Subscribe to our YouTube Channel",
        "link": "https://www.youtube.com/channel/UCq9m8BB7232mODFet-RYBMg",
		"newTab": "YES",
		"png": "img/social-youtube.png",
		"id": "youtube"
      },
	  {
        "name": "Hear us jamming on Spotify",
        "link": "https://open.spotify.com/user/j106iy85afhlykc8hypra33po",
		"newTab": "YES",
		"png": "img/social-spotify.png",
		"id": "spotify"
      }
    ]
  },
  {
    "buttons": [
      {
        "name": "Facebook Group",
        "icon": "Icon ID",
        "link": "LINK"
      }
    ]
  }
]
